empiricalfin/__init__.py
empiricalfin/template.docx
empiricalfin/sorting/__init__.py
empiricalfin/sorting/_double_sorting.py
empiricalfin/sorting/_old_region_sorting.py
empiricalfin/sorting/_old_single_sorting.py
empiricalfin/sorting/_region_sorting.py
empiricalfin/sorting/_renders.py
empiricalfin/sorting/_single_sorting.py
empiricalfin/sorting/_utils.py
py_empirical_fin-0.4.5.dist-info/METADATA
py_empirical_fin-0.4.5.dist-info/WHEEL
py_empirical_fin-0.4.5.dist-info/top_level.txt
py_empirical_fin-0.4.5.dist-info/RECORD
