Metadata-Version: 2.1
Name: py_empirical_fin
Version: 0.4.5
Summary: tools for empirical finance
Home-page: 
Author: lester-zhang
Author-email: lester.zhang99@gmail.com
Classifier: Programming Language :: Python :: 3
Classifier: License :: OSI Approved :: MIT License
Classifier: Operating System :: OS Independent
Requires-Python: >=3.6
Requires-Dist: pandas
Requires-Dist: numpy
Requires-Dist: statsmodels
Requires-Dist: python-docx
